atomicio/__init__.py
atomicio/__main__.py
atomicio/core.py
atomicio/defaults.py
atomicio/formats.py
atomicio/version.py
atomicio-1.0.1.dist-info/entry_points.txt
atomicio-1.0.1.dist-info/licenses/LICENSE
atomicio-1.0.1.dist-info/METADATA
atomicio-1.0.1.dist-info/WHEEL
atomicio-1.0.1.dist-info/RECORD
