Metadata-Version: 2.4
Name: atomicio
Version: 1.0.1
Summary: Thread-safe, async-safe, and atomic file operations with extensible format support for Python
License: MIT
License-File: LICENSE
Keywords: atomic,file-operations,thread-safe,async,locking,concurrent,file-locking,safe-write,data-integrity
Author: Santiago Matta
Author-email: santiagomatta@outlook.cl
Requires-Python: >=3.8
Classifier: Development Status :: 5 - Production/Stable
Classifier: Framework :: AsyncIO
Classifier: Framework :: FastAPI
Classifier: Intended Audience :: Developers
Classifier: License :: OSI Approved :: MIT License
Classifier: Natural Language :: English
Classifier: Operating System :: MacOS
Classifier: Operating System :: Microsoft :: Windows
Classifier: Operating System :: OS Independent
Classifier: Operating System :: POSIX :: Linux
Classifier: Programming Language :: Python :: 3
Classifier: Programming Language :: Python :: 3.8
Classifier: Programming Language :: Python :: 3.9
Classifier: Programming Language :: Python :: 3.10
Classifier: Programming Language :: Python :: 3.11
Classifier: Programming Language :: Python :: 3.12
Classifier: Programming Language :: Python :: 3.13
Classifier: Programming Language :: Python :: 3.14
Classifier: Topic :: Software Development :: Libraries
Classifier: Topic :: Software Development :: Libraries :: Python Modules
Classifier: Topic :: System :: Filesystems
Classifier: Typing :: Typed
Requires-Dist: filelock (>=3.12.0)
Requires-Dist: pyyaml (>=6.0.1)
Requires-Dist: tomli (>=2.0.1) ; python_version < "3.11"
Requires-Dist: tomli_w (>=1.0.0)
Project-URL: Documentation, https://github.com/santiago897/atomicio-project/blob/main/README.md
Project-URL: Homepage, https://github.com/santiago897/atomicio-project
Project-URL: Repository, https://github.com/santiago897/atomicio-project
Project-URL: homepage, https://github.com/santiago897/atomicio-project
